datools/__init__.py
datools/cli.py
datools/datools.py
datools/errors.py
datools/explanations.py
datools/models.py
datools/sqlalchemy_utils.py
datools/table_statistics.py
datools-0.1.5.dist-info/AUTHORS.md
datools-0.1.5.dist-info/LICENSE
datools-0.1.5.dist-info/METADATA
datools-0.1.5.dist-info/WHEEL
datools-0.1.5.dist-info/entry_points.txt
datools-0.1.5.dist-info/top_level.txt
datools-0.1.5.dist-info/RECORD
