Metadata-Version: 2.1
Name: datools
Version: 0.1.5
Summary: Some tools for working with data
Home-page: https://github.com/marcua/datools
Author: Adam Marcus
Author-email: marcua@marcua.net
License: Apache Software License 2.0
Keywords: datools
Platform: UNKNOWN
Classifier: Development Status :: 2 - Pre-Alpha
Classifier: Intended Audience :: Developers
Classifier: License :: OSI Approved :: Apache Software License
Classifier: Natural Language :: English
Classifier: Programming Language :: Python :: 3.6
Classifier: Programming Language :: Python :: 3.7
Classifier: Programming Language :: Python :: 3.8
Classifier: Programming Language :: Python :: 3.9
Classifier: Programming Language :: Python :: 3.10
Requires-Python: >=3.6
Requires-Dist: Click (>=7.0)
Requires-Dist: sqlalchemy (==1.4.17)
Requires-Dist: tabulate (==0.8.9)
Requires-Dist: dataclasses ; python_version < "3.7"
